{
    "builder": {
        "--source": "./examples/data_of_contents/battle_sequence_of_unfair_cointoss.step5_auto_split_by_pillar.json"
    },
    "compiler": {
        "objectFolder": "./temp/examples",
        "objectFilePrefix": null,
        "tlanslators": {
            "autoSplitSegmentByPillar": {
                "enabled": true,
                "objectFile": {
                    "write": true,
                    "suffix": "after_auto_split_by_pillar"
                }
            },
            "autoShadow": {
                "enabled": true,
                "objectFile": {
                    "write": true,
                    "suffix": "after_auto_shadow"
                }
            },
            "imports": {
                "enabled": true,
                "objectFile": {
                    "write": true,
                    "suffix": "after_imports"
                }
            }
        }
    },
    "renderer": {
        "--output": "./temp/examples/no5_auto_split_pillar.xlsx",
        "features": {
        }
    }
}